pcsinfo/Computer.py
pcsinfo/User.py
pcsinfo/__init__.py
pcsinfo-0.1.3.dist-info/METADATA
pcsinfo-0.1.3.dist-info/WHEEL
pcsinfo-0.1.3.dist-info/top_level.txt
pcsinfo-0.1.3.dist-info/RECORD
