Metadata-Version: 2.1
Name: pcsinfo
Version: 0.1.3
Summary: A easy module for obtaining information about a PC
Home-page: https://github.com/barlin41k/pcsinfo
Author: barlin41k
Author-email: sasaigrypocta@gmail.com
Project-URL: GitHub, https://github.com/barlin41k/pcsinfo
